{
    "Compline_0": {
        "parent": "Compline",
        "summary": "Compline",
        "start time": "2021-10-01 21:45",
        "end time": "2021-10-01 22:00",
        "kind": "Spirituality",
        "sub kind": "Liturgy",
        "movable": "True",
        "squishable": "False",
        "early bound": "20:30",
        "late bound": "23:30",
        "description": "",
        "tags": [
            "prayer"
        ]
    },
    "Sleep_0": {
        "parent": "Sleep",
        "summary": "Sleep",
        "start time": "2021-10-01 22:30",
        "end time": "2021-10-02 06:45",
        "kind": "Sleep",
        "sub kind": "",
        "movable": "False",
        "squishable": "False",
        "description": "",
        "tags": [
            "sleep"
        ]
    },
    "Compline_1": {
        "parent": "Compline",
        "summary": "Compline",
        "start time": "2021-10-02 21:45",
        "end time": "2021-10-02 22:00",
        "kind": "Spirituality",
        "sub kind": "Liturgy",
        "movable": "True",
        "squishable": "False",
        "early bound": "20:30",
        "late bound": "23:30",
        "description": "",
        "tags": [
            "prayer"
        ]
    },
    "Sleep_1": {
        "parent": "Sleep",
        "summary": "Sleep",
        "start time": "2021-10-02 22:30",
        "end time": "2021-10-03 06:45",
        "kind": "Sleep",
        "sub kind": "",
        "movable": "False",
        "squishable": "False",
        "description": "",
        "tags": [
            "sleep"
        ]
    },
    "Compline_2": {
        "parent": "Compline",
        "summary": "Compline",
        "start time": "2021-10-03 21:45",
        "end time": "2021-10-03 22:00",
        "kind": "Spirituality",
        "sub kind": "Liturgy",
        "movable": "True",
        "squishable": "False",
        "early bound": "20:30",
        "late bound": "23:30",
        "description": "",
        "tags": [
            "prayer"
        ]
    },
    "Sleep_2": {
        "parent": "Sleep",
        "summary": "Sleep",
        "start time": "2021-10-03 22:30",
        "end time": "2021-10-04 06:45",
        "kind": "Sleep",
        "sub kind": "",
        "movable": "False",
        "squishable": "False",
        "description": "",
        "tags": [
            "sleep"
        ]
    },
    "Philosophy of Science_0": {
        "parent": "Philosophy of Science",
        "summary": "Philosophy of Science",
        "start time": "2021-10-04 15:30",
        "end time": "2021-10-04 16:45",
        "kind": "Class",
        "sub kind": "Philosophy",
        "movable": "False",
        "squishable": "False",
        "description": "",
        "tags": [
            "philosophy",
            "class"
        ]
    },
    "Compline_3": {
        "parent": "Compline",
        "summary": "Compline",
        "start time": "2021-10-04 21:45",
        "end time": "2021-10-04 22:00",
        "kind": "Spirituality",
        "sub kind": "Liturgy",
        "movable": "True",
        "squishable": "False",
        "early bound": "20:30",
        "late bound": "23:30",
        "description": "",
        "tags": [
            "prayer"
        ]
    },
    "Sleep_3": {
        "parent": "Sleep",
        "summary": "Sleep",
        "start time": "2021-10-04 22:30",
        "end time": "2021-10-05 06:45",
        "kind": "Sleep",
        "sub kind": "",
        "movable": "False",
        "squishable": "False",
        "description": "",
        "tags": [
            "sleep"
        ]
    },
    "Discourse on the porch_0": {
        "parent": "Discourse on the porch",
        "summary": "Discourse on the porch",
        "start time": "2021-10-05 15:00",
        "end time": "2021-10-05 16:00",
        "kind": "Socializing",
        "sub kind": "Fraternity",
        "movable": "True",
        "squishable": "True",
        "minimum duration": "15",
        "description": "",
        "tags": [
            "fellowship"
        ]
    },
    "Compline_4": {
        "parent": "Compline",
        "summary": "Compline",
        "start time": "2021-10-05 21:45",
        "end time": "2021-10-05 22:00",
        "kind": "Spirituality",
        "sub kind": "Liturgy",
        "movable": "True",
        "squishable": "False",
        "early bound": "20:30",
        "late bound": "23:30",
        "description": "",
        "tags": [
            "prayer"
        ]
    },
    "Sleep_4": {
        "parent": "Sleep",
        "summary": "Sleep",
        "start time": "2021-10-05 22:30",
        "end time": "2021-10-06 06:45",
        "kind": "Sleep",
        "sub kind": "",
        "movable": "False",
        "squishable": "False",
        "description": "",
        "tags": [
            "sleep"
        ]
    },
    "Discourse on the porch_1": {
        "parent": "Discourse on the porch",
        "summary": "Discourse on the porch",
        "start time": "2021-10-06 15:00",
        "end time": "2021-10-06 16:00",
        "kind": "Socializing",
        "sub kind": "Fraternity",
        "movable": "True",
        "squishable": "True",
        "minimum duration": "15",
        "description": "",
        "tags": [
            "fellowship"
        ]
    },
    "Philosophy of Science_1": {
        "parent": "Philosophy of Science",
        "summary": "Philosophy of Science",
        "start time": "2021-10-06 15:30",
        "end time": "2021-10-06 16:45",
        "kind": "Class",
        "sub kind": "Philosophy",
        "movable": "False",
        "squishable": "False",
        "description": "",
        "tags": [
            "philosophy",
            "class"
        ]
    },
    "Compline_5": {
        "parent": "Compline",
        "summary": "Compline",
        "start time": "2021-10-06 21:45",
        "end time": "2021-10-06 22:00",
        "kind": "Spirituality",
        "sub kind": "Liturgy",
        "movable": "True",
        "squishable": "False",
        "early bound": "20:30",
        "late bound": "23:30",
        "description": "",
        "tags": [
            "prayer"
        ]
    },
    "Sleep_5": {
        "parent": "Sleep",
        "summary": "Sleep",
        "start time": "2021-10-06 22:30",
        "end time": "2021-10-07 06:45",
        "kind": "Sleep",
        "sub kind": "",
        "movable": "False",
        "squishable": "False",
        "description": "",
        "tags": [
            "sleep"
        ]
    },
    "Compline_6": {
        "parent": "Compline",
        "summary": "Compline",
        "start time": "2021-10-07 21:45",
        "end time": "2021-10-07 22:00",
        "kind": "Spirituality",
        "sub kind": "Liturgy",
        "movable": "True",
        "squishable": "False",
        "early bound": "20:30",
        "late bound": "23:30",
        "description": "",
        "tags": [
            "prayer"
        ]
    },
    "Sleep_6": {
        "parent": "Sleep",
        "summary": "Sleep",
        "start time": "2021-10-07 22:30",
        "end time": "2021-10-08 06:45",
        "kind": "Sleep",
        "sub kind": "",
        "movable": "False",
        "squishable": "False",
        "description": "",
        "tags": [
            "sleep"
        ]
    },
    "Compline_7": {
        "parent": "Compline",
        "summary": "Compline",
        "start time": "2021-10-08 21:45",
        "end time": "2021-10-08 22:00",
        "kind": "Spirituality",
        "sub kind": "Liturgy",
        "movable": "True",
        "squishable": "False",
        "early bound": "20:30",
        "late bound": "23:30",
        "description": "",
        "tags": [
            "prayer"
        ]
    },
    "Sleep_7": {
        "parent": "Sleep",
        "summary": "Sleep",
        "start time": "2021-10-08 22:30",
        "end time": "2021-10-09 06:45",
        "kind": "Sleep",
        "sub kind": "",
        "movable": "False",
        "squishable": "False",
        "description": "",
        "tags": [
            "sleep"
        ]
    },
    "Compline_8": {
        "parent": "Compline",
        "summary": "Compline",
        "start time": "2021-10-09 21:45",
        "end time": "2021-10-09 22:00",
        "kind": "Spirituality",
        "sub kind": "Liturgy",
        "movable": "True",
        "squishable": "False",
        "early bound": "20:30",
        "late bound": "23:30",
        "description": "",
        "tags": [
            "prayer"
        ]
    },
    "Sleep_8": {
        "parent": "Sleep",
        "summary": "Sleep",
        "start time": "2021-10-09 22:30",
        "end time": "2021-10-10 06:45",
        "kind": "Sleep",
        "sub kind": "",
        "movable": "False",
        "squishable": "False",
        "description": "",
        "tags": [
            "sleep"
        ]
    },
    "Compline_9": {
        "parent": "Compline",
        "summary": "Compline",
        "start time": "2021-10-10 21:45",
        "end time": "2021-10-10 22:00",
        "kind": "Spirituality",
        "sub kind": "Liturgy",
        "movable": "True",
        "squishable": "False",
        "early bound": "20:30",
        "late bound": "23:30",
        "description": "",
        "tags": [
            "prayer"
        ]
    },
    "Sleep_9": {
        "parent": "Sleep",
        "summary": "Sleep",
        "start time": "2021-10-10 22:30",
        "end time": "2021-10-11 06:45",
        "kind": "Sleep",
        "sub kind": "",
        "movable": "False",
        "squishable": "False",
        "description": "",
        "tags": [
            "sleep"
        ]
    },
    "Philosophy of Science_2": {
        "parent": "Philosophy of Science",
        "summary": "Philosophy of Science",
        "start time": "2021-10-11 15:30",
        "end time": "2021-10-11 16:45",
        "kind": "Class",
        "sub kind": "Philosophy",
        "movable": "False",
        "squishable": "False",
        "description": "",
        "tags": [
            "philosophy",
            "class"
        ]
    },
    "Compline_10": {
        "parent": "Compline",
        "summary": "Compline",
        "start time": "2021-10-11 21:45",
        "end time": "2021-10-11 22:00",
        "kind": "Spirituality",
        "sub kind": "Liturgy",
        "movable": "True",
        "squishable": "False",
        "early bound": "20:30",
        "late bound": "23:30",
        "description": "",
        "tags": [
            "prayer"
        ]
    },
    "Sleep_10": {
        "parent": "Sleep",
        "summary": "Sleep",
        "start time": "2021-10-11 22:30",
        "end time": "2021-10-12 06:45",
        "kind": "Sleep",
        "sub kind": "",
        "movable": "False",
        "squishable": "False",
        "description": "",
        "tags": [
            "sleep"
        ]
    },
    "Discourse on the porch_2": {
        "parent": "Discourse on the porch",
        "summary": "Discourse on the porch",
        "start time": "2021-10-12 15:00",
        "end time": "2021-10-12 16:00",
        "kind": "Socializing",
        "sub kind": "Fraternity",
        "movable": "True",
        "squishable": "True",
        "minimum duration": "15",
        "description": "",
        "tags": [
            "fellowship"
        ]
    },
    "Compline_11": {
        "parent": "Compline",
        "summary": "Compline",
        "start time": "2021-10-12 21:45",
        "end time": "2021-10-12 22:00",
        "kind": "Spirituality",
        "sub kind": "Liturgy",
        "movable": "True",
        "squishable": "False",
        "early bound": "20:30",
        "late bound": "23:30",
        "description": "",
        "tags": [
            "prayer"
        ]
    },
    "Sleep_11": {
        "parent": "Sleep",
        "summary": "Sleep",
        "start time": "2021-10-12 22:30",
        "end time": "2021-10-13 06:45",
        "kind": "Sleep",
        "sub kind": "",
        "movable": "False",
        "squishable": "False",
        "description": "",
        "tags": [
            "sleep"
        ]
    },
    "Discourse on the porch_3": {
        "parent": "Discourse on the porch",
        "summary": "Discourse on the porch",
        "start time": "2021-10-13 15:00",
        "end time": "2021-10-13 16:00",
        "kind": "Socializing",
        "sub kind": "Fraternity",
        "movable": "True",
        "squishable": "True",
        "minimum duration": "15",
        "description": "",
        "tags": [
            "fellowship"
        ]
    },
    "Philosophy of Science_3": {
        "parent": "Philosophy of Science",
        "summary": "Philosophy of Science",
        "start time": "2021-10-13 15:30",
        "end time": "2021-10-13 16:45",
        "kind": "Class",
        "sub kind": "Philosophy",
        "movable": "False",
        "squishable": "False",
        "description": "",
        "tags": [
            "philosophy",
            "class"
        ]
    },
    "Compline_12": {
        "parent": "Compline",
        "summary": "Compline",
        "start time": "2021-10-13 21:45",
        "end time": "2021-10-13 22:00",
        "kind": "Spirituality",
        "sub kind": "Liturgy",
        "movable": "True",
        "squishable": "False",
        "early bound": "20:30",
        "late bound": "23:30",
        "description": "",
        "tags": [
            "prayer"
        ]
    },
    "Sleep_12": {
        "parent": "Sleep",
        "summary": "Sleep",
        "start time": "2021-10-13 22:30",
        "end time": "2021-10-14 06:45",
        "kind": "Sleep",
        "sub kind": "",
        "movable": "False",
        "squishable": "False",
        "description": "",
        "tags": [
            "sleep"
        ]
    },
    "Compline_13": {
        "parent": "Compline",
        "summary": "Compline",
        "start time": "2021-10-14 21:45",
        "end time": "2021-10-14 22:00",
        "kind": "Spirituality",
        "sub kind": "Liturgy",
        "movable": "True",
        "squishable": "False",
        "early bound": "20:30",
        "late bound": "23:30",
        "description": "",
        "tags": [
            "prayer"
        ]
    },
    "Sleep_13": {
        "parent": "Sleep",
        "summary": "Sleep",
        "start time": "2021-10-14 22:30",
        "end time": "2021-10-15 06:45",
        "kind": "Sleep",
        "sub kind": "",
        "movable": "False",
        "squishable": "False",
        "description": "",
        "tags": [
            "sleep"
        ]
    },
    "Compline_14": {
        "parent": "Compline",
        "summary": "Compline",
        "start time": "2021-10-15 21:45",
        "end time": "2021-10-15 22:00",
        "kind": "Spirituality",
        "sub kind": "Liturgy",
        "movable": "True",
        "squishable": "False",
        "early bound": "20:30",
        "late bound": "23:30",
        "description": "",
        "tags": [
            "prayer"
        ]
    },
    "Sleep_14": {
        "parent": "Sleep",
        "summary": "Sleep",
        "start time": "2021-10-15 22:30",
        "end time": "2021-10-16 06:45",
        "kind": "Sleep",
        "sub kind": "",
        "movable": "False",
        "squishable": "False",
        "description": "",
        "tags": [
            "sleep"
        ]
    },
    "Compline_15": {
        "parent": "Compline",
        "summary": "Compline",
        "start time": "2021-10-16 21:45",
        "end time": "2021-10-16 22:00",
        "kind": "Spirituality",
        "sub kind": "Liturgy",
        "movable": "True",
        "squishable": "False",
        "early bound": "20:30",
        "late bound": "23:30",
        "description": "",
        "tags": [
            "prayer"
        ]
    },
    "Sleep_15": {
        "parent": "Sleep",
        "summary": "Sleep",
        "start time": "2021-10-16 22:30",
        "end time": "2021-10-17 06:45",
        "kind": "Sleep",
        "sub kind": "",
        "movable": "False",
        "squishable": "False",
        "description": "",
        "tags": [
            "sleep"
        ]
    },
    "Compline_16": {
        "parent": "Compline",
        "summary": "Compline",
        "start time": "2021-10-17 21:45",
        "end time": "2021-10-17 22:00",
        "kind": "Spirituality",
        "sub kind": "Liturgy",
        "movable": "True",
        "squishable": "False",
        "early bound": "20:30",
        "late bound": "23:30",
        "description": "",
        "tags": [
            "prayer"
        ]
    },
    "Sleep_16": {
        "parent": "Sleep",
        "summary": "Sleep",
        "start time": "2021-10-17 22:30",
        "end time": "2021-10-18 06:45",
        "kind": "Sleep",
        "sub kind": "",
        "movable": "False",
        "squishable": "False",
        "description": "",
        "tags": [
            "sleep"
        ]
    },
    "Philosophy of Science_4": {
        "parent": "Philosophy of Science",
        "summary": "Philosophy of Science",
        "start time": "2021-10-18 15:30",
        "end time": "2021-10-18 16:45",
        "kind": "Class",
        "sub kind": "Philosophy",
        "movable": "False",
        "squishable": "False",
        "description": "",
        "tags": [
            "philosophy",
            "class"
        ]
    },
    "Compline_17": {
        "parent": "Compline",
        "summary": "Compline",
        "start time": "2021-10-18 21:45",
        "end time": "2021-10-18 22:00",
        "kind": "Spirituality",
        "sub kind": "Liturgy",
        "movable": "True",
        "squishable": "False",
        "early bound": "20:30",
        "late bound": "23:30",
        "description": "",
        "tags": [
            "prayer"
        ]
    },
    "Sleep_17": {
        "parent": "Sleep",
        "summary": "Sleep",
        "start time": "2021-10-18 22:30",
        "end time": "2021-10-19 06:45",
        "kind": "Sleep",
        "sub kind": "",
        "movable": "False",
        "squishable": "False",
        "description": "",
        "tags": [
            "sleep"
        ]
    },
    "Discourse on the porch_4": {
        "parent": "Discourse on the porch",
        "summary": "Discourse on the porch",
        "start time": "2021-10-19 15:00",
        "end time": "2021-10-19 16:00",
        "kind": "Socializing",
        "sub kind": "Fraternity",
        "movable": "True",
        "squishable": "True",
        "minimum duration": "15",
        "description": "",
        "tags": [
            "fellowship"
        ]
    },
    "Compline_18": {
        "parent": "Compline",
        "summary": "Compline",
        "start time": "2021-10-19 21:45",
        "end time": "2021-10-19 22:00",
        "kind": "Spirituality",
        "sub kind": "Liturgy",
        "movable": "True",
        "squishable": "False",
        "early bound": "20:30",
        "late bound": "23:30",
        "description": "",
        "tags": [
            "prayer"
        ]
    },
    "Sleep_18": {
        "parent": "Sleep",
        "summary": "Sleep",
        "start time": "2021-10-19 22:30",
        "end time": "2021-10-20 06:45",
        "kind": "Sleep",
        "sub kind": "",
        "movable": "False",
        "squishable": "False",
        "description": "",
        "tags": [
            "sleep"
        ]
    },
    "Discourse on the porch_5": {
        "parent": "Discourse on the porch",
        "summary": "Discourse on the porch",
        "start time": "2021-10-20 15:00",
        "end time": "2021-10-20 16:00",
        "kind": "Socializing",
        "sub kind": "Fraternity",
        "movable": "True",
        "squishable": "True",
        "minimum duration": "15",
        "description": "",
        "tags": [
            "fellowship"
        ]
    },
    "Philosophy of Science_5": {
        "parent": "Philosophy of Science",
        "summary": "Philosophy of Science",
        "start time": "2021-10-20 15:30",
        "end time": "2021-10-20 16:45",
        "kind": "Class",
        "sub kind": "Philosophy",
        "movable": "False",
        "squishable": "False",
        "description": "",
        "tags": [
            "philosophy",
            "class"
        ]
    },
    "Compline_19": {
        "parent": "Compline",
        "summary": "Compline",
        "start time": "2021-10-20 21:45",
        "end time": "2021-10-20 22:00",
        "kind": "Spirituality",
        "sub kind": "Liturgy",
        "movable": "True",
        "squishable": "False",
        "early bound": "20:30",
        "late bound": "23:30",
        "description": "",
        "tags": [
            "prayer"
        ]
    },
    "Sleep_19": {
        "parent": "Sleep",
        "summary": "Sleep",
        "start time": "2021-10-20 22:30",
        "end time": "2021-10-21 06:45",
        "kind": "Sleep",
        "sub kind": "",
        "movable": "False",
        "squishable": "False",
        "description": "",
        "tags": [
            "sleep"
        ]
    },
    "Compline_20": {
        "parent": "Compline",
        "summary": "Compline",
        "start time": "2021-10-21 21:45",
        "end time": "2021-10-21 22:00",
        "kind": "Spirituality",
        "sub kind": "Liturgy",
        "movable": "True",
        "squishable": "False",
        "early bound": "20:30",
        "late bound": "23:30",
        "description": "",
        "tags": [
            "prayer"
        ]
    },
    "Sleep_20": {
        "parent": "Sleep",
        "summary": "Sleep",
        "start time": "2021-10-21 22:30",
        "end time": "2021-10-22 06:45",
        "kind": "Sleep",
        "sub kind": "",
        "movable": "False",
        "squishable": "False",
        "description": "",
        "tags": [
            "sleep"
        ]
    },
    "Compline_21": {
        "parent": "Compline",
        "summary": "Compline",
        "start time": "2021-10-22 21:45",
        "end time": "2021-10-22 22:00",
        "kind": "Spirituality",
        "sub kind": "Liturgy",
        "movable": "True",
        "squishable": "False",
        "early bound": "20:30",
        "late bound": "23:30",
        "description": "",
        "tags": [
            "prayer"
        ]
    },
    "Sleep_21": {
        "parent": "Sleep",
        "summary": "Sleep",
        "start time": "2021-10-22 22:30",
        "end time": "2021-10-23 06:45",
        "kind": "Sleep",
        "sub kind": "",
        "movable": "False",
        "squishable": "False",
        "description": "",
        "tags": [
            "sleep"
        ]
    },
    "Compline_22": {
        "parent": "Compline",
        "summary": "Compline",
        "start time": "2021-10-23 21:45",
        "end time": "2021-10-23 22:00",
        "kind": "Spirituality",
        "sub kind": "Liturgy",
        "movable": "True",
        "squishable": "False",
        "early bound": "20:30",
        "late bound": "23:30",
        "description": "",
        "tags": [
            "prayer"
        ]
    },
    "Sleep_22": {
        "parent": "Sleep",
        "summary": "Sleep",
        "start time": "2021-10-23 22:30",
        "end time": "2021-10-24 06:45",
        "kind": "Sleep",
        "sub kind": "",
        "movable": "False",
        "squishable": "False",
        "description": "",
        "tags": [
            "sleep"
        ]
    },
    "Compline_23": {
        "parent": "Compline",
        "summary": "Compline",
        "start time": "2021-10-24 21:45",
        "end time": "2021-10-24 22:00",
        "kind": "Spirituality",
        "sub kind": "Liturgy",
        "movable": "True",
        "squishable": "False",
        "early bound": "20:30",
        "late bound": "23:30",
        "description": "",
        "tags": [
            "prayer"
        ]
    },
    "Sleep_23": {
        "parent": "Sleep",
        "summary": "Sleep",
        "start time": "2021-10-24 22:30",
        "end time": "2021-10-25 06:45",
        "kind": "Sleep",
        "sub kind": "",
        "movable": "False",
        "squishable": "False",
        "description": "",
        "tags": [
            "sleep"
        ]
    },
    "Philosophy of Science_6": {
        "parent": "Philosophy of Science",
        "summary": "Philosophy of Science",
        "start time": "2021-10-25 15:30",
        "end time": "2021-10-25 16:45",
        "kind": "Class",
        "sub kind": "Philosophy",
        "movable": "False",
        "squishable": "False",
        "description": "",
        "tags": [
            "philosophy",
            "class"
        ]
    },
    "Compline_24": {
        "parent": "Compline",
        "summary": "Compline",
        "start time": "2021-10-25 21:45",
        "end time": "2021-10-25 22:00",
        "kind": "Spirituality",
        "sub kind": "Liturgy",
        "movable": "True",
        "squishable": "False",
        "early bound": "20:30",
        "late bound": "23:30",
        "description": "",
        "tags": [
            "prayer"
        ]
    },
    "Sleep_24": {
        "parent": "Sleep",
        "summary": "Sleep",
        "start time": "2021-10-25 22:30",
        "end time": "2021-10-26 06:45",
        "kind": "Sleep",
        "sub kind": "",
        "movable": "False",
        "squishable": "False",
        "description": "",
        "tags": [
            "sleep"
        ]
    },
    "Metaphysics_0": {
        "parent": "Metaphysics",
        "summary": "Metaphysics",
        "start time": "2021-10-26 13:30",
        "end time": "2021-10-26 14:45",
        "kind": "Class",
        "sub kind": "Philosophy",
        "movable": "False",
        "squishable": "False",
        "early bound": "13:00",
        "late bound": "15:15",
        "description": "",
        "tags": [
            "philosophy",
            "class"
        ]
    },
    "Discourse on the porch_6": {
        "parent": "Discourse on the porch",
        "summary": "Discourse on the porch",
        "start time": "2021-10-26 15:00",
        "end time": "2021-10-26 16:00",
        "kind": "Socializing",
        "sub kind": "Fraternity",
        "movable": "True",
        "squishable": "True",
        "minimum duration": "15",
        "description": "",
        "tags": [
            "fellowship"
        ]
    },
    "Compline_25": {
        "parent": "Compline",
        "summary": "Compline",
        "start time": "2021-10-26 21:45",
        "end time": "2021-10-26 22:00",
        "kind": "Spirituality",
        "sub kind": "Liturgy",
        "movable": "True",
        "squishable": "False",
        "early bound": "20:30",
        "late bound": "23:30",
        "description": "",
        "tags": [
            "prayer"
        ]
    },
    "Sleep_25": {
        "parent": "Sleep",
        "summary": "Sleep",
        "start time": "2021-10-26 22:30",
        "end time": "2021-10-27 06:45",
        "kind": "Sleep",
        "sub kind": "",
        "movable": "False",
        "squishable": "False",
        "description": "",
        "tags": [
            "sleep"
        ]
    },
    "Metaphysics_1": {
        "parent": "Metaphysics",
        "summary": "Metaphysics",
        "start time": "2021-10-27 13:30",
        "end time": "2021-10-27 14:45",
        "kind": "Class",
        "sub kind": "Philosophy",
        "movable": "False",
        "squishable": "False",
        "early bound": "13:00",
        "late bound": "15:15",
        "description": "",
        "tags": [
            "philosophy",
            "class"
        ]
    },
    "Discourse on the porch_7": {
        "parent": "Discourse on the porch",
        "summary": "Discourse on the porch",
        "start time": "2021-10-27 15:00",
        "end time": "2021-10-27 16:00",
        "kind": "Socializing",
        "sub kind": "Fraternity",
        "movable": "True",
        "squishable": "True",
        "minimum duration": "15",
        "description": "",
        "tags": [
            "fellowship"
        ]
    },
    "Philosophy of Science_7": {
        "parent": "Philosophy of Science",
        "summary": "Philosophy of Science",
        "start time": "2021-10-27 15:30",
        "end time": "2021-10-27 16:45",
        "kind": "Class",
        "sub kind": "Philosophy",
        "movable": "False",
        "squishable": "False",
        "description": "",
        "tags": [
            "philosophy",
            "class"
        ]
    },
    "Compline_26": {
        "parent": "Compline",
        "summary": "Compline",
        "start time": "2021-10-27 21:45",
        "end time": "2021-10-27 22:00",
        "kind": "Spirituality",
        "sub kind": "Liturgy",
        "movable": "True",
        "squishable": "False",
        "early bound": "20:30",
        "late bound": "23:30",
        "description": "",
        "tags": [
            "prayer"
        ]
    },
    "Sleep_26": {
        "parent": "Sleep",
        "summary": "Sleep",
        "start time": "2021-10-27 22:30",
        "end time": "2021-10-28 06:45",
        "kind": "Sleep",
        "sub kind": "",
        "movable": "False",
        "squishable": "False",
        "description": "",
        "tags": [
            "sleep"
        ]
    },
    "Metaphysics_2": {
        "parent": "Metaphysics",
        "summary": "Metaphysics",
        "start time": "2021-10-28 13:30",
        "end time": "2021-10-28 14:45",
        "kind": "Class",
        "sub kind": "Philosophy",
        "movable": "False",
        "squishable": "False",
        "early bound": "13:00",
        "late bound": "15:15",
        "description": "",
        "tags": [
            "philosophy",
            "class"
        ]
    },
    "Compline_27": {
        "parent": "Compline",
        "summary": "Compline",
        "start time": "2021-10-28 21:45",
        "end time": "2021-10-28 22:00",
        "kind": "Spirituality",
        "sub kind": "Liturgy",
        "movable": "True",
        "squishable": "False",
        "early bound": "20:30",
        "late bound": "23:30",
        "description": "",
        "tags": [
            "prayer"
        ]
    },
    "Sleep_27": {
        "parent": "Sleep",
        "summary": "Sleep",
        "start time": "2021-10-28 22:30",
        "end time": "2021-10-29 06:45",
        "kind": "Sleep",
        "sub kind": "",
        "movable": "False",
        "squishable": "False",
        "description": "",
        "tags": [
            "sleep"
        ]
    },
    "Metaphysics_3": {
        "parent": "Metaphysics",
        "summary": "Metaphysics",
        "start time": "2021-10-29 13:30",
        "end time": "2021-10-29 14:45",
        "kind": "Class",
        "sub kind": "Philosophy",
        "movable": "False",
        "squishable": "False",
        "early bound": "13:00",
        "late bound": "15:15",
        "description": "",
        "tags": [
            "philosophy",
            "class"
        ]
    },
    "Compline_28": {
        "parent": "Compline",
        "summary": "Compline",
        "start time": "2021-10-29 21:45",
        "end time": "2021-10-29 22:00",
        "kind": "Spirituality",
        "sub kind": "Liturgy",
        "movable": "True",
        "squishable": "False",
        "early bound": "20:30",
        "late bound": "23:30",
        "description": "",
        "tags": [
            "prayer"
        ]
    },
    "Sleep_28": {
        "parent": "Sleep",
        "summary": "Sleep",
        "start time": "2021-10-29 22:30",
        "end time": "2021-10-30 06:45",
        "kind": "Sleep",
        "sub kind": "",
        "movable": "False",
        "squishable": "False",
        "description": "",
        "tags": [
            "sleep"
        ]
    },
    "Compline_29": {
        "parent": "Compline",
        "summary": "Compline",
        "start time": "2021-10-30 21:45",
        "end time": "2021-10-30 22:00",
        "kind": "Spirituality",
        "sub kind": "Liturgy",
        "movable": "True",
        "squishable": "False",
        "early bound": "20:30",
        "late bound": "23:30",
        "description": "",
        "tags": [
            "prayer"
        ]
    },
    "Sleep_29": {
        "parent": "Sleep",
        "summary": "Sleep",
        "start time": "2021-10-30 22:30",
        "end time": "2021-10-31 06:45",
        "kind": "Sleep",
        "sub kind": "",
        "movable": "False",
        "squishable": "False",
        "description": "",
        "tags": [
            "sleep"
        ]
    },
    "Compline_30": {
        "parent": "Compline",
        "summary": "Compline",
        "start time": "2021-10-31 21:45",
        "end time": "2021-10-31 22:00",
        "kind": "Spirituality",
        "sub kind": "Liturgy",
        "movable": "True",
        "squishable": "False",
        "early bound": "20:30",
        "late bound": "23:30",
        "description": "",
        "tags": [
            "prayer"
        ]
    },
    "Sleep_30": {
        "parent": "Sleep",
        "summary": "Sleep",
        "start time": "2021-10-31 22:30",
        "end time": "2021-11-01 06:45",
        "kind": "Sleep",
        "sub kind": "",
        "movable": "False",
        "squishable": "False",
        "description": "",
        "tags": [
            "sleep"
        ]
    },
    "Philosophy of Science_8": {
        "parent": "Philosophy of Science",
        "summary": "Philosophy of Science",
        "start time": "2021-11-01 15:30",
        "end time": "2021-11-01 16:45",
        "kind": "Class",
        "sub kind": "Philosophy",
        "movable": "False",
        "squishable": "False",
        "description": "",
        "tags": [
            "philosophy",
            "class"
        ]
    },
    "Compline_31": {
        "parent": "Compline",
        "summary": "Compline",
        "start time": "2021-11-01 21:45",
        "end time": "2021-11-01 22:00",
        "kind": "Spirituality",
        "sub kind": "Liturgy",
        "movable": "True",
        "squishable": "False",
        "early bound": "20:30",
        "late bound": "23:30",
        "description": "",
        "tags": [
            "prayer"
        ]
    },
    "Sleep_31": {
        "parent": "Sleep",
        "summary": "Sleep",
        "start time": "2021-11-01 22:30",
        "end time": "2021-11-02 06:45",
        "kind": "Sleep",
        "sub kind": "",
        "movable": "False",
        "squishable": "False",
        "description": "",
        "tags": [
            "sleep"
        ]
    },
    "Sleep_32": {
        "parent": "Sleep",
        "summary": "Sleep",
        "start time": "2021-11-02 22:30",
        "end time": "2021-11-03 06:45",
        "kind": "Sleep",
        "sub kind": "",
        "movable": "False",
        "squishable": "False",
        "description": "",
        "tags": [
            "sleep"
        ]
    },
    "Philosophy of Science_9": {
        "parent": "Philosophy of Science",
        "summary": "Philosophy of Science",
        "start time": "2021-11-03 15:30",
        "end time": "2021-11-03 16:45",
        "kind": "Class",
        "sub kind": "Philosophy",
        "movable": "False",
        "squishable": "False",
        "description": "",
        "tags": [
            "philosophy",
            "class"
        ]
    },
    "Sleep_33": {
        "parent": "Sleep",
        "summary": "Sleep",
        "start time": "2021-11-03 22:30",
        "end time": "2021-11-04 06:45",
        "kind": "Sleep",
        "sub kind": "",
        "movable": "False",
        "squishable": "False",
        "description": "",
        "tags": [
            "sleep"
        ]
    },
    "Sleep_34": {
        "parent": "Sleep",
        "summary": "Sleep",
        "start time": "2021-11-04 22:30",
        "end time": "2021-11-05 06:45",
        "kind": "Sleep",
        "sub kind": "",
        "movable": "False",
        "squishable": "False",
        "description": "",
        "tags": [
            "sleep"
        ]
    },
    "Philosophy of Science_10": {
        "parent": "Philosophy of Science",
        "summary": "Philosophy of Science",
        "start time": "2021-11-08 15:30",
        "end time": "2021-11-08 16:45",
        "kind": "Class",
        "sub kind": "Philosophy",
        "movable": "False",
        "squishable": "False",
        "description": "",
        "tags": [
            "philosophy",
            "class"
        ]
    },
    "Philosophy of Science_11": {
        "parent": "Philosophy of Science",
        "summary": "Philosophy of Science",
        "start time": "2021-11-10 15:30",
        "end time": "2021-11-10 16:45",
        "kind": "Class",
        "sub kind": "Philosophy",
        "movable": "False",
        "squishable": "False",
        "description": "",
        "tags": [
            "philosophy",
            "class"
        ]
    },
    "Philosophy of Science_12": {
        "parent": "Philosophy of Science",
        "summary": "Philosophy of Science",
        "start time": "2021-11-15 15:30",
        "end time": "2021-11-15 16:45",
        "kind": "Class",
        "sub kind": "Philosophy",
        "movable": "False",
        "squishable": "False",
        "description": "",
        "tags": [
            "philosophy",
            "class"
        ]
    },
    "Philosophy of Science_13": {
        "parent": "Philosophy of Science",
        "summary": "Philosophy of Science",
        "start time": "2021-11-17 15:30",
        "end time": "2021-11-17 16:45",
        "kind": "Class",
        "sub kind": "Philosophy",
        "movable": "False",
        "squishable": "False",
        "description": "",
        "tags": [
            "philosophy",
            "class"
        ]
    },
    "Philosophy of Science_14": {
        "parent": "Philosophy of Science",
        "summary": "Philosophy of Science",
        "start time": "2021-11-22 15:30",
        "end time": "2021-11-22 16:45",
        "kind": "Class",
        "sub kind": "Philosophy",
        "movable": "False",
        "squishable": "False",
        "description": "",
        "tags": [
            "philosophy",
            "class"
        ]
    },
    "Philosophy of Science_15": {
        "parent": "Philosophy of Science",
        "summary": "Philosophy of Science",
        "start time": "2021-11-24 15:30",
        "end time": "2021-11-24 16:45",
        "kind": "Class",
        "sub kind": "Philosophy",
        "movable": "False",
        "squishable": "False",
        "description": "",
        "tags": [
            "philosophy",
            "class"
        ]
    }
}